.gitignore
.travis.yml
LICENSE
README.md
bld.bat
build.sh
distr.sh
meta.yaml
quantan.iss
requirements.txt
requirements_conda.txt
requirements_pip.txt
setup.cfg
setup.py
.idea/vcs.xml
quantan/__init__.py
quantan/__main__.py
quantan/histology_analyser_gui.py
quantan/histology_report.py
quantan/quantan.py
quantan.egg-info/PKG-INFO
quantan.egg-info/SOURCES.txt
quantan.egg-info/dependency_links.txt
quantan.egg-info/pbr.json
quantan.egg-info/requires.txt
quantan.egg-info/top_level.txt
quantan/icon/icon.ico
quantan/icon/icon.png
quantan/icon/icon.svg
quantan/icon/icon512.ico
quantan/icon/icon512.png
tests/hist_stats_test.yaml
tests/histology_test.py
tests/vt_biodur.yaml