Metadata-Version: 1.1
Name: quantan
Version: 0.0.23
Summary: Quantitative histological analyser
Home-page: https://github.com/mjirik/quanta
Author: Miroslav Jirik and Pavel Volkovinsky
Author-email: miroslav.jirik@gmail.com
License: MIT
Keywords: dicom 3D read write
Platform: UNKNOWN
Classifier: Development Status :: 3 - Alpha
Classifier: Intended Audience :: Developers
Classifier: Topic :: Scientific/Engineering :: Bio-Informatics
Classifier: License :: OSI Approved :: BSD License
Classifier: Programming Language :: Python :: 2.7
